{
  "project_info": {
    "project_number": "583951388896",
    "firebase_url": "https://boiteaah.firebaseio.com",
    "project_id": "boiteaah",
    "storage_bucket": "boiteaah.appspot.com"
  },
  "client": [
    {
      "client_info": {
        "mobilesdk_app_id": "1:583951388896:android:e306f729e8819e7f",
        "android_client_info": {
          "package_name": "com.monirapps.boiteaah"
        }
      },
      "oauth_client": [
        {
          "client_id": "583951388896-0mas3gjk8ig71kcm5kuhu0a1vfe8oae9.apps.googleusercontent.com",
          "client_type": 3
        }
      ],
      "api_key": [
        {
          "current_key": "AIzaSyBQzMiOlLaTeGrvhyampbEOFfvsF966hq8"
        }
      ],
      "services": {
        "analytics_service": {
          "status": 1
        },
        "appinvite_service": {
          "status": 1,
          "other_platform_oauth_client": []
        },
        "ads_service": {
          "status": 2
        }
      }
    }
  ],
  "configuration_version": "1"
}